sscv/__init__.py
sscv/utils.py
sscv/psdAnn/__init__.py
sscv/psdAnn/coco_utils.py
sscv/psdAnn/converters.py
sscv/psdAnn/psd-to-coco.py
sscv/psdAnn/utils.py
sscv-0.1.20.dist-info/LICENSE
sscv-0.1.20.dist-info/METADATA
sscv-0.1.20.dist-info/WHEEL
sscv-0.1.20.dist-info/top_level.txt
sscv-0.1.20.dist-info/RECORD
