Metadata-Version: 2.1
Name: sscv
Version: 0.1.20
Summary: Open computer vision libary for strucutral health monitoring
Home-page: https://github.com/SSSL-at-UOS/sscv
Author: Byunghyun Kim
Author-email: kimbh.mail@gmail.com
License: MIT
Platform: UNKNOWN
Classifier: Programming Language :: Python :: 3
Classifier: Programming Language :: Python :: 3.2
Classifier: Programming Language :: Python :: 3.3
Classifier: Programming Language :: Python :: 3.4
Classifier: Programming Language :: Python :: 3.5
Classifier: Programming Language :: Python :: 3.6
Classifier: Programming Language :: Python :: 3.7
Classifier: License :: OSI Approved :: MIT License
Classifier: Operating System :: OS Independent
